{
  "version": "7",
  "dialect": "postgresql",
  "entries": [
    {
      "idx": 0,
      "version": "7",
      "when": 1768979739885,
      "tag": "0000_swift_quicksilver",
      "breakpoints": true
    },
    {
      "idx": 3,
      "version": "7",
      "when": 1764754730507,
      "tag": "0003_panoramic_the_anarchist",
      "breakpoints": true
    },
    {
      "idx": 4,
      "version": "7",
      "when": 1769543589896,
      "tag": "0004_green_shadowcat",
      "breakpoints": true
    }
  ]
}